ajtest/__init__.py
ajtest/module1.py
ajtest/module2.py
ajtest-0.0.1.dist-info/LICENSE
ajtest-0.0.1.dist-info/METADATA
ajtest-0.0.1.dist-info/WHEEL
ajtest-0.0.1.dist-info/top_level.txt
ajtest-0.0.1.dist-info/RECORD
